arxiv_dl/__init__.py
arxiv_dl/__main__.py
arxiv_dl/dl_utils.py
arxiv_dl/helpers.py
arxiv_dl/models.py
arxiv_dl/printer.py
arxiv_dl/scrapers.py
arxiv_dl/target_parser.py
arxiv_dl/updater.py
arxiv_dl-1.2.2.dist-info/METADATA
arxiv_dl-1.2.2.dist-info/WHEEL
arxiv_dl-1.2.2.dist-info/entry_points.txt
arxiv_dl-1.2.2.dist-info/licenses/LICENSE
arxiv_dl-1.2.2.dist-info/RECORD
