Metadata-Version: 2.4
Name: arxiv-dl
Version: 1.2.2
Summary: Command-line Papers Downloader. Citation extraction and PDF naming automation.
Project-URL: Homepage, https://github.com/MarkHershey/arxiv-dl
Project-URL: Issues, https://github.com/MarkHershey/arxiv-dl/issues
Author-email: Mark He Huang <dev@markhh.com>
License: MIT License
License-File: LICENSE
Keywords: CVF,CVPR,ECCV,ICCV,WACV,arxiv,downloader,paper
Classifier: License :: OSI Approved :: MIT License
Classifier: Natural Language :: English
Classifier: Operating System :: OS Independent
Classifier: Programming Language :: Python :: 3
Classifier: Topic :: Utilities
Requires-Python: >=3.6
Requires-Dist: beautifulsoup4
Requires-Dist: pydantic
Requires-Dist: pymupdf
Requires-Dist: requests
Requires-Dist: rich
Provides-Extra: dev
Requires-Dist: black; extra == 'dev'
Requires-Dist: check-manifest; extra == 'dev'
Requires-Dist: isort; extra == 'dev'
Requires-Dist: pytest; extra == 'dev'
Requires-Dist: tox; extra == 'dev'
Requires-Dist: twine; extra == 'dev'
Requires-Dist: wheel; extra == 'dev'
